pylicy/__init__.py
pylicy/models.py
pylicy/policy.py
pylicy/pylicy.py
pylicy/rules.py
pylicy/utils.py
pylicy-0.1.1.dist-info/LICENSE
pylicy-0.1.1.dist-info/WHEEL
pylicy-0.1.1.dist-info/METADATA
pylicy-0.1.1.dist-info/RECORD
