Metadata-Version: 2.1
Name: pylicy
Version: 0.1.1
Summary: Extensible and customizable policy definition and enforcement framework
Home-page: https://github.com/uint0/pylicy
License: MIT
Author: uint0
Author-email: chen@czhou.me
Requires-Python: >=3.9,<4.0
Classifier: License :: OSI Approved :: MIT License
Classifier: Programming Language :: Python :: 3
Classifier: Programming Language :: Python :: 3.10
Classifier: Programming Language :: Python :: 3.9
Requires-Dist: PyYAML (>=6.0,<7.0)
Requires-Dist: pydantic (>=1.8.2,<2.0.0)
Project-URL: Repository, https://github.com/uint0/pylicy
